ErCore/Core.py
ErCore/__init__.py
ErCore/cli.py
ErCore/std/Base.py
ErCore/std/__init__.py
ErCore-1.5.dist-info/LICENSE
ErCore-1.5.dist-info/METADATA
ErCore-1.5.dist-info/WHEEL
ErCore-1.5.dist-info/entry_points.txt
ErCore-1.5.dist-info/top_level.txt
ErCore-1.5.dist-info/RECORD
