Metadata-Version: 2.1
Name: ErCore
Version: 1.5
Summary: Core for projects
Home-page: https://github.com/Eragod/ErCore
Author: Eragod
Classifier: Programming Language :: Python :: 3
Classifier: License :: OSI Approved :: MIT License
Classifier: Operating System :: OS Independent
License-File: LICENSE
